cruds_mixins/__init__.py
cruds_mixins/conf.py
cruds_mixins/models.py
cruds_mixins/urls.py
cruds_mixins/locale/en/LC_MESSAGES/django.mo
cruds_mixins/locale/en/LC_MESSAGES/django.po
cruds_mixins/locale/sl/LC_MESSAGES/django.mo
cruds_mixins/locale/sl/LC_MESSAGES/django.po
cruds_mixins/mixins/__init__.py
cruds_mixins/mixins/bulk_actions.py
cruds_mixins/mixins/cruds.py
cruds_mixins/mixins/export.py
cruds_mixins/mixins/filter_mixin.py
cruds_mixins/mixins/navigation.py
cruds_mixins/mixins/tables.py
cruds_mixins/permission_classes/__init__.py
cruds_mixins/static/cruds_mixins/css/cruds_mixins.css
cruds_mixins/static/cruds_mixins/js/cruds_mixins.js
cruds_mixins/tables/__init__.py
cruds_mixins/tables/columns.py
cruds_mixins/tables/tables.py
cruds_mixins/templates/cruds_mixins/base.html
cruds_mixins/templates/cruds_mixins/bulk_selection_form.html
cruds_mixins/templates/cruds_mixins/delete.html
cruds_mixins/templates/cruds_mixins/detail.html
cruds_mixins/templates/cruds_mixins/form.html
cruds_mixins/templates/cruds_mixins/list.html
cruds_mixins/templates/cruds_mixins/partials/actions.html
cruds_mixins/templates/cruds_mixins/partials/bulk_actions.html
cruds_mixins/templates/cruds_mixins/partials/filter.html
cruds_mixins/templates/cruds_mixins/partials/messages.html
cruds_mixins/templates/cruds_mixins/partials/pagination.html
cruds_mixins/templates/cruds_mixins/partials/table.html
cruds_mixins/templatetags/__init__.py
cruds_mixins/templatetags/paginator_helper_tags.py
cruds_mixins/utils/__init__.py
cruds_mixins/utils/filters.py
cruds_mixins/utils/pagination.py
cruds_mixins/utils/rules.py
cruds_mixins/utils/text.py
cruds_mixins/views/__init__.py
cruds_mixins/views/crud.py
django_cruds_mixins-3.0.0.dist-info/AUTHORS.rst
django_cruds_mixins-3.0.0.dist-info/LICENSE
django_cruds_mixins-3.0.0.dist-info/METADATA
django_cruds_mixins-3.0.0.dist-info/WHEEL
django_cruds_mixins-3.0.0.dist-info/top_level.txt
django_cruds_mixins-3.0.0.dist-info/RECORD
