Metadata-Version: 2.1
Name: django-cruds-mixins
Version: 3.0.0
Summary: Fast and predicatable creation of admin panels and applications
Home-page: https://github.com/bmihelac/django-cruds-mixins
Author: Bojan Mihelac
Author-email: bmihelac@mihelac.org
Keywords: django-cruds-mixins
Classifier: Development Status :: 3 - Alpha
Classifier: Framework :: Django
Classifier: Framework :: Django :: 2.0
Classifier: Intended Audience :: Developers
Classifier: License :: OSI Approved :: BSD License
Classifier: Natural Language :: English
Classifier: Programming Language :: Python :: 3.4
Classifier: Programming Language :: Python :: 3.5
Classifier: Programming Language :: Python :: 3.6
License-File: LICENSE
License-File: AUTHORS.rst
Requires-Dist: Django <5,>=4.2
Requires-Dist: rules ==3.3
Requires-Dist: django-tables2 ==2.4.1
Requires-Dist: django-appconf ==1.0.5
Requires-Dist: django-filter ==2.4.0
Requires-Dist: django-crispy-forms ==1.14.0
Requires-Dist: django-cruds <4,>=3.0
Requires-Dist: django-import-export <3,>=2.8.0
